pullapprove/__init__.py
pullapprove/checklists.py
pullapprove/cli.py
pullapprove/config.py
pullapprove/diff.py
pullapprove/exceptions.py
pullapprove/git.py
pullapprove/matches.py
pullapprove/printer.py
pullapprove/results_migrations.py
pullapprove-5.5.0.dist-info/METADATA
pullapprove-5.5.0.dist-info/WHEEL
pullapprove-5.5.0.dist-info/entry_points.txt
pullapprove-5.5.0.dist-info/RECORD
