Metadata-Version: 2.4
Name: pullapprove
Version: 5.5.0
Summary: CLI for PullApprove5
Project-URL: Homepage, https://www.pullapprove.com?ref=pypi
Project-URL: Documentation, https://5.pullapprove.com/docs/?ref=pypi
Author-email: Dropseed <python@dropseed.dev>
Classifier: Development Status :: 5 - Production/Stable
Classifier: Environment :: Console
Classifier: Intended Audience :: Developers
Classifier: Programming Language :: Python :: 3
Classifier: Programming Language :: Python :: 3.12
Classifier: Programming Language :: Python :: 3.13
Classifier: Topic :: Software Development :: Version Control :: Git
Requires-Python: >=3.12
Requires-Dist: click>=8
Requires-Dist: pydantic>=2
Requires-Dist: requests>=2
Requires-Dist: wcmatch>=8.0
